Metadata-Version: 2.1
Name: zilian-mssql-django
Version: 1.1.2
Summary: Django backend for Microsoft SQL Server
Home-page: https://github.com/microsoft/mssql-django
Author: Microsoft
Author-email: opencode@microsoft.com
License: BSD
Project-URL: Release Notes, https://github.com/microsoft/mssql-django/releases
Keywords: django
Platform: UNKNOWN
Classifier: License :: OSI Approved :: BSD License
Classifier: Framework :: Django
Classifier: Operating System :: POSIX :: Linux
Classifier: Operating System :: Microsoft :: Windows
Classifier: Programming Language :: Python
Classifier: Programming Language :: Python :: 3
Classifier: Programming Language :: Python :: 3.6
Classifier: Programming Language :: Python :: 3.7
Classifier: Programming Language :: Python :: 3.8
Classifier: Programming Language :: Python :: 3.9
Classifier: Framework :: Django :: 2.2
Classifier: Framework :: Django :: 3.0
Classifier: Framework :: Django :: 3.1
Classifier: Framework :: Django :: 3.2
Classifier: Framework :: Django :: 4.0
